[
  {
    "text": "中华树艺师学会",
    "score": 0.8054104447364807,
    "box": [
      [
        55.0,
        54.0
      ],
      [
        450.0,
        60.0
      ],
      [
        449.0,
        112.0
      ],
      [
        54.0,
        107.0
      ]
    ]
  },
  {
    "text": "确定组织架构",
    "score": 0.9607537388801575,
    "box": [
      [
        54.0,
        120.0
      ],
      [
        391.0,
        125.0
      ],
      [
        390.0,
        176.0
      ],
      [
        53.0,
        172.0
      ]
    ]
  },
  {
    "text": "本报讯（记者周昆）11月6日，记者从",
    "score": 0.9325989484786987,
    "box": [
      [
        98.0,
        211.0
      ],
      [
        494.0,
        218.0
      ],
      [
        493.0,
        241.0
      ],
      [
        97.0,
        235.0
      ]
    ]
  },
  {
    "text": "位于香港的中华树艺师学会（CAA）获悉，该",
    "score": 0.8905608057975769,
    "box": [
      [
        50.0,
        243.0
      ],
      [
        494.0,
        249.0
      ],
      [
        494.0,
        270.0
      ],
      [
        50.0,
        264.0
      ]
    ]
  },
  {
    "text": "学会刚刚完成了包括核心人员构成、章程、",
    "score": 0.9151891469955444,
    "box": [
      [
        49.0,
        273.0
      ],
      [
        492.0,
        280.0
      ],
      [
        491.0,
        304.0
      ],
      [
        49.0,
        296.0
      ]
    ]
  },
  {
    "text": "管理制度等相关组织架构的确定工作，正式",
    "score": 0.9158432483673096,
    "box": [
      [
        48.0,
        302.0
      ],
      [
        494.0,
        310.0
      ],
      [
        493.0,
        334.0
      ],
      [
        48.0,
        327.0
      ]
    ]
  },
  {
    "text": "运营进入了倒计时阶段。",
    "score": 0.9301237463951111,
    "box": [
      [
        48.0,
        335.0
      ],
      [
        296.0,
        339.0
      ],
      [
        296.0,
        362.0
      ],
      [
        48.0,
        358.0
      ]
    ]
  },
  {
    "text": "中华树艺师学会的前身是“国际树木学",
    "score": 0.9530609250068665,
    "box": [
      [
        97.0,
        367.0
      ],
      [
        492.0,
        372.0
      ],
      [
        492.0,
        394.0
      ],
      [
        96.0,
        388.0
      ]
    ]
  },
  {
    "text": "会中国地区分会”。中华树艺师学会由创始",
    "score": 0.9111180305480957,
    "box": [
      [
        48.0,
        396.0
      ],
      [
        492.0,
        402.0
      ],
      [
        492.0,
        426.0
      ],
      [
        48.0,
        421.0
      ]
    ]
  },
  {
    "text": "人欧永森担任会长，副会长由拥有30多年",
    "score": 0.9766964912414551,
    "box": [
      [
        49.0,
        430.0
      ],
      [
        491.0,
        436.0
      ],
      [
        491.0,
        456.0
      ],
      [
        49.0,
        450.0
      ]
    ]
  },
  {
    "text": "行业经验的李沛森担任。",
    "score": 0.9484663605690002,
    "box": [
      [
        47.0,
        459.0
      ],
      [
        294.0,
        463.0
      ],
      [
        294.0,
        485.0
      ],
      [
        47.0,
        480.0
      ]
    ]
  },
  {
    "text": "该学会采取会员制管理，欧永森表示，",
    "score": 0.9264757037162781,
    "box": [
      [
        94.0,
        491.0
      ],
      [
        492.0,
        495.0
      ],
      [
        492.0,
        519.0
      ],
      [
        93.0,
        515.0
      ]
    ]
  },
  {
    "text": "他们会从普通会员中选拔受过训练和持有",
    "score": 0.969939649105072,
    "box": [
      [
        46.0,
        520.0
      ],
      [
        491.0,
        526.0
      ],
      [
        491.0,
        549.0
      ],
      [
        46.0,
        543.0
      ]
    ]
  },
  {
    "text": "从业执照的人，并授予其专业会员的荣誉，",
    "score": 0.9333543181419373,
    "box": [
      [
        46.0,
        550.0
      ],
      [
        488.0,
        557.0
      ],
      [
        488.0,
        582.0
      ],
      [
        46.0,
        574.0
      ]
    ]
  },
  {
    "text": "这个上升通道将激发会员自我提升的积极",
    "score": 0.9317617416381836,
    "box": [
      [
        46.0,
        584.0
      ],
      [
        490.0,
        590.0
      ],
      [
        490.0,
        610.0
      ],
      [
        46.0,
        604.0
      ]
    ]
  },
  {
    "text": "性。据了解，该学会成立至今，共注册了2300",
    "score": 0.9427270889282227,
    "box": [
      [
        44.0,
        613.0
      ],
      [
        492.0,
        619.0
      ],
      [
        492.0,
        642.0
      ],
      [
        44.0,
        636.0
      ]
    ]
  },
  {
    "text": "多名会员。",
    "score": 0.9890438318252563,
    "box": [
      [
        45.0,
        642.0
      ],
      [
        153.0,
        645.0
      ],
      [
        152.0,
        670.0
      ],
      [
        44.0,
        667.0
      ]
    ]
  },
  {
    "text": "本次组织架构的确定也将中文树艺培",
    "score": 0.9385093450546265,
    "box": [
      [
        94.0,
        676.0
      ],
      [
        490.0,
        681.0
      ],
      [
        490.0,
        702.0
      ],
      [
        93.0,
        697.0
      ]
    ]
  },
  {
    "text": "训和证书认证工作做了细化。如考试内容一",
    "score": 0.9157142639160156,
    "box": [
      [
        45.0,
        707.0
      ],
      [
        488.0,
        713.0
      ],
      [
        488.0,
        733.0
      ],
      [
        45.0,
        727.0
      ]
    ]
  },
  {
    "text": "改以往只有选择题的单一模式，加人了简答",
    "score": 0.9133327603340149,
    "box": [
      [
        45.0,
        737.0
      ],
      [
        488.0,
        744.0
      ],
      [
        488.0,
        764.0
      ],
      [
        45.0,
        758.0
      ]
    ]
  },
  {
    "text": "题和论述报告。此外，在“树艺技师牌照”考",
    "score": 0.9375954866409302,
    "box": [
      [
        44.0,
        768.0
      ],
      [
        488.0,
        774.0
      ],
      [
        488.0,
        795.0
      ],
      [
        44.0,
        789.0
      ]
    ]
  },
  {
    "text": "试中还加人了树上用锯、锯木溜缆和空中",
    "score": 0.9520320892333984,
    "box": [
      [
        44.0,
        799.0
      ],
      [
        487.0,
        806.0
      ],
      [
        487.0,
        827.0
      ],
      [
        44.0,
        819.0
      ]
    ]
  },
  {
    "text": "拯救等实用技能的考核。",
    "score": 0.9354944229125977,
    "box": [
      [
        44.0,
        829.0
      ],
      [
        291.0,
        834.0
      ],
      [
        291.0,
        855.0
      ],
      [
        43.0,
        851.0
      ]
    ]
  }
]